cinet/__init__.py
cinet/interfaces.py
cinet/models.py
cinet/testing_utils/00_simple_train_test.py
cinet/testing_utils/01_hparam_tuning.py
cinet/testing_utils/02_results_after_tuning.py
cinet/testing_utils/03_compare.py
cinet/utils.py
cinet-0.0.16.dist-info/LICENSE
cinet-0.0.16.dist-info/WHEEL
cinet-0.0.16.dist-info/METADATA
cinet-0.0.16.dist-info/RECORD
