Metadata-Version: 2.1
Name: cinet
Version: 0.0.16
Summary: Scikit-Learn interface for CINET PyTorch siamese neural network
License: MIT
Author: Christopher Eeles
Requires-Python: >=3.9,<4.0
Classifier: License :: OSI Approved :: MIT License
Classifier: Programming Language :: Python :: 3
Classifier: Programming Language :: Python :: 3.9
Classifier: Programming Language :: Python :: 3.10
Classifier: Programming Language :: Python :: 3.11
Requires-Dist: ConfigSpace (>=0.5.0,<0.6.0)
Requires-Dist: lifelines (>=0.27.1,<0.28.0)
Requires-Dist: numpy (>=1.23.0,<2.0.0)
Requires-Dist: pandas (>=1.4.3,<2.0.0)
Requires-Dist: pytorch-lightning (>=1.6.4,<2.0.0)
Requires-Dist: ray (>=1.13.0,<2.0.0)
Requires-Dist: sklearn (>=0.0,<0.1)
Requires-Dist: tabulate (>=0.8.10,<0.9.0)
Requires-Dist: torch (>=1.11.0,<2.0.0)
